flask_zipkin.py
Flask_Zipkin-0.0.5.dist-info/METADATA
Flask_Zipkin-0.0.5.dist-info/WHEEL
Flask_Zipkin-0.0.5.dist-info/top_level.txt
Flask_Zipkin-0.0.5.dist-info/RECORD
