Metadata-Version: 2.1
Name: Flask-Zipkin
Version: 0.0.5
Summary: An zipkin extension for Flask based on py_zipkin.
Home-page: https://github.com/qiajigou/flask-zipkin
Author: killpanda
Author-email: angus@killpanda.de
License: BSD
Platform: any
Requires-Dist: Flask
Requires-Dist: py-zipkin (>=0.13.0)
Requires-Dist: requests (>=2.11.1)
